db_operationsss/__init__.py
db_operationsss/db_operations.py
db_operationsss-0.1.dist-info/METADATA
db_operationsss-0.1.dist-info/WHEEL
db_operationsss-0.1.dist-info/top_level.txt
db_operationsss-0.1.dist-info/RECORD
