Metadata-Version: 2.1
Name: db-operationsss
Version: 0.1
Summary: A library for performing database operations with PostgreSQL
Home-page: https://github.com/Unberkannt/db_operationsss
Author: Unberkannt
Author-email: unberkannt@mail.ru
Classifier: Programming Language :: Python :: 3
Classifier: License :: OSI Approved :: MIT License
Classifier: Operating System :: OS Independent
Requires-Python: >=3.6
Requires-Dist: psycopg2
